{
  "id": "asobi-asobase-ova-1548",
  "title": "Asobi Asobase OVA",
  "malID": 37996,
  "alID": 0,
  "image": "https://img.flawlessfiles.com/_r/300x400/100/28/1b/281bf2872167a4156c37557ecdb5c4cc/281bf2872167a4156c37557ecdb5c4cc.jpg",
  "description": "Included with seventh volume of the Asobi Asobase manga.",
  "type": "OVA",
  "url": "https://aniwatch.to/asobi-asobase-ova-1548",
  "subOrDub": "sub",
  "hasSub": true,
  "totalEpisodes": 1,
  "episodes": [
    {
      "id": "asobi-asobase-ova-1548$episode$91109$sub",
      "number": 1,
      "title": "Full",
      "isFiller": false,
      "url": "https://aniwatch.to/watch/asobi-asobase-ova-1548?ep=91109"
    }
  ]
}