{
  "id": "back-arrow-15650",
  "title": "Back Arrow",
  "malID": 40964,
  "alID": 114307,
  "image": "https://img.flawlessfiles.com/_r/300x400/100/a0/79/a0798537328d2f4f3a729f1f4b5e85fb/a0798537328d2f4f3a729f1f4b5e85fb.jpg",
  "description": "The world of Lingalind is surrounded by a mystical wall with seemingly nothing beyond its confines. Worshipped as the mother of the land, the wall delivers celestial gift capsules called \"Rakuho'' to locations across the continent. Arriving once a month, the capsules contain metallic armbands that allow the wearer to transform into a mechanical being known as a \"Briheight.\" As a result, Lingalind is thrown into constant turmoil by its warring nations, all hoping to strengthen their military prowess by procuring the offerings for themselves.\n\nOne day, a Rakuho crash-lands in the countryside with an unexpected inhabitant—a mysterious black-haired man. All eyes are set on this strange newcomer, who calls himself \"Back Arrow,\" when he claims to have hailed from a place beyond the wall—a revelation that can potentially unravel Lingalind's entire dogmatic foundation.\n\n[Written by MAL Rewrite]",
  "type": "TV",
  "url": "https://aniwatch.to/back-arrow-15650",
  "subOrDub": "both",
  "hasSub": true,
  "hasDub": true,
  "totalEpisodes": 24,
  "episodes": [
    {
      "id": "back-arrow-15650$episode$54780$both",
      "number": 1,
      "title": "Do Guys from the Sky Have Undies?",
      "isFiller": false,
      "url": "https://aniwatch.to/watch/back-arrow-15650?ep=54780"
    },
    {
      "id": "back-arrow-15650$episode$54781$both",
      "number": 2,
      "title": "Is Having Dreams a Burden?",
      "isFiller": false,
      "url": "https://aniwatch.to/watch/back-arrow-15650?ep=54781"
    },
    {
      "id": "back-arrow-15650$episode$54782$both",
      "number": 3,
      "title": "Does a Huge Ship Bring Hope?",
      "isFiller": false,
      "url": "https://aniwatch.to/watch/back-arrow-15650?ep=54782"
    },
    {
      "id": "back-arrow-15650$episode$54783$both",
      "number": 4,
      "title": "Does Genius Come When Least Expected?",
      "isFiller": false,
      "url": "https://aniwatch.to/watch/back-arrow-15650?ep=54783"
    },
    {
      "id": "back-arrow-15650$episode$54784$both",
      "number": 5,
      "title": "Is Today Yesterday`s Tomorrow?",
      "isFiller": false,
      "url": "https://aniwatch.to/watch/back-arrow-15650?ep=54784"
    },
    {
      "id": "back-arrow-15650$episode$54785$both",
      "number": 6,
      "title": "Are Pretty Boy Farms a Thing?",
      "isFiller": false,
      "url": "https://aniwatch.to/watch/back-arrow-15650?ep=54785"
    },
    {
      "id": "back-arrow-15650$episode$54786$both",
      "number": 7,
      "title": "Is the Wall Really That Solid?",
      "isFiller": false,
      "url": "https://aniwatch.to/watch/back-arrow-15650?ep=54786"
    },
    {
      "id": "back-arrow-15650$episode$54787$both",
      "number": 8,
      "title": "What Is the Bloodstained Knight Hiding?",
      "isFiller": false,
      "url": "https://aniwatch.to/watch/back-arrow-15650?ep=54787"
    },
    {
      "id": "back-arrow-15650$episode$54788$both",
      "number": 9,
      "title": "Why Do Lips That Profess Love Hide Fangs?",
      "isFiller": false,
      "url": "https://aniwatch.to/watch/back-arrow-15650?ep=54788"
    },
    {
      "id": "back-arrow-15650$episode$54789$both",
      "number": 10,
      "title": "Can Have-Nots Have Backbone?",
      "isFiller": false,
      "url": "https://aniwatch.to/watch/back-arrow-15650?ep=54789"
    },
    {
      "id": "back-arrow-15650$episode$54790$both",
      "number": 11,
      "title": "Is This a Head-to-Head Fight?",
      "isFiller": false,
      "url": "https://aniwatch.to/watch/back-arrow-15650?ep=54790"
    },
    {
      "id": "back-arrow-15650$episode$64544$both",
      "number": 12,
      "title": "Is Too Much Pride A Problem?",
      "isFiller": false,
      "url": "https://aniwatch.to/watch/back-arrow-15650?ep=64544"
    },
    {
      "id": "back-arrow-15650$episode$64546$both",
      "number": 13,
      "title": "Do the Heavens Cry When the Princess Rises?",
      "isFiller": false,
      "url": "https://aniwatch.to/watch/back-arrow-15650?ep=64546"
    },
    {
      "id": "back-arrow-15650$episode$64548$both",
      "number": 14,
      "title": "Is There Love on the Battlefield?",
      "isFiller": false,
      "url": "https://aniwatch.to/watch/back-arrow-15650?ep=64548"
    },
    {
      "id": "back-arrow-15650$episode$64550$both",
      "number": 15,
      "title": "What Will the Riots Produce?",
      "isFiller": false,
      "url": "https://aniwatch.to/watch/back-arrow-15650?ep=64550"
    },
    {
      "id": "back-arrow-15650$episode$64553$both",
      "number": 16,
      "title": "When People Want Peace, What Does God Want?",
      "isFiller": false,
      "url": "https://aniwatch.to/watch/back-arrow-15650?ep=64553"
    },
    {
      "id": "back-arrow-15650$episode$64556$both",
      "number": 17,
      "title": "So Will They Stand Up?",
      "isFiller": false,
      "url": "https://aniwatch.to/watch/back-arrow-15650?ep=64556"
    },
    {
      "id": "back-arrow-15650$episode$69598$both",
      "number": 18,
      "title": "Is This the World's Truth?",
      "isFiller": false,
      "url": "https://aniwatch.to/watch/back-arrow-15650?ep=69598"
    },
    {
      "id": "back-arrow-15650$episode$71448$both",
      "number": 19,
      "title": "Can You Sort This Out?",
      "isFiller": false,
      "url": "https://aniwatch.to/watch/back-arrow-15650?ep=71448"
    },
    {
      "id": "back-arrow-15650$episode$72017$both",
      "number": 20,
      "title": "Does People's Anger Reach God?",
      "isFiller": false,
      "url": "https://aniwatch.to/watch/back-arrow-15650?ep=72017"
    },
    {
      "id": "back-arrow-15650$episode$72657$both",
      "number": 21,
      "title": "Who Will Stop Me?",
      "isFiller": false,
      "url": "https://aniwatch.to/watch/back-arrow-15650?ep=72657"
    },
    {
      "id": "back-arrow-15650$episode$73455$both",
      "number": 22,
      "title": "But What Do I Live For?",
      "isFiller": false,
      "url": "https://aniwatch.to/watch/back-arrow-15650?ep=73455"
    },
    {
      "id": "back-arrow-15650$episode$74075$both",
      "number": 23,
      "title": "Does Destruction Rain From the Heavens?",
      "isFiller": false,
      "url": "https://aniwatch.to/watch/back-arrow-15650?ep=74075"
    },
    {
      "id": "back-arrow-15650$episode$75724$both",
      "number": 24,
      "title": "Do We Head for the Stars?",
      "isFiller": false,
      "url": "https://aniwatch.to/watch/back-arrow-15650?ep=75724"
    }
  ]
}