{
  "id": "everlasting-immortal-firmament-3482",
  "title": "Everlasting Immortal Firmament",
  "malID": 36148,
  "alID": 0,
  "image": "https://img.flawlessfiles.com/_r/300x400/100/d7/fa/d7faa7619b55154142b05e85b4ae497a/d7faa7619b55154142b05e85b4ae497a.jpg",
  "description": "Heavenly Dao is eternal, however life is limited, making heaven and earth pieces of a chessboard.\n\nGu Hai from the 21st century was taken onto another world. Gu Hai became a formidable opponent in the area of trade. In the times of war, he comes up with strategies for the Chen Empire against the Song Empire.\n\nA fairy from heaven became interested in him and gave him a mission to complete on his journey. However this may bring turmoil and chaos upon the world.",
  "type": "ONA",
  "url": "https://aniwatch.to/everlasting-immortal-firmament-3482",
  "subOrDub": "sub",
  "hasSub": true,
  "totalEpisodes": 12,
  "episodes": [
    {
      "id": "everlasting-immortal-firmament-3482$episode$102457$sub",
      "number": 1,
      "title": "Episode 1",
      "isFiller": false,
      "url": "https://aniwatch.to/watch/everlasting-immortal-firmament-3482?ep=102457"
    },
    {
      "id": "everlasting-immortal-firmament-3482$episode$102458$sub",
      "number": 2,
      "title": "Episode 2",
      "isFiller": false,
      "url": "https://aniwatch.to/watch/everlasting-immortal-firmament-3482?ep=102458"
    },
    {
      "id": "everlasting-immortal-firmament-3482$episode$102459$sub",
      "number": 3,
      "title": "Episode 3",
      "isFiller": false,
      "url": "https://aniwatch.to/watch/everlasting-immortal-firmament-3482?ep=102459"
    },
    {
      "id": "everlasting-immortal-firmament-3482$episode$102460$sub",
      "number": 4,
      "title": "Episode 4",
      "isFiller": false,
      "url": "https://aniwatch.to/watch/everlasting-immortal-firmament-3482?ep=102460"
    },
    {
      "id": "everlasting-immortal-firmament-3482$episode$102461$sub",
      "number": 5,
      "title": "Episode 5",
      "isFiller": false,
      "url": "https://aniwatch.to/watch/everlasting-immortal-firmament-3482?ep=102461"
    },
    {
      "id": "everlasting-immortal-firmament-3482$episode$102462$sub",
      "number": 6,
      "title": "Episode 6",
      "isFiller": false,
      "url": "https://aniwatch.to/watch/everlasting-immortal-firmament-3482?ep=102462"
    },
    {
      "id": "everlasting-immortal-firmament-3482$episode$102463$sub",
      "number": 7,
      "title": "Episode 7",
      "isFiller": false,
      "url": "https://aniwatch.to/watch/everlasting-immortal-firmament-3482?ep=102463"
    },
    {
      "id": "everlasting-immortal-firmament-3482$episode$102464$sub",
      "number": 8,
      "title": "Episode 8",
      "isFiller": false,
      "url": "https://aniwatch.to/watch/everlasting-immortal-firmament-3482?ep=102464"
    },
    {
      "id": "everlasting-immortal-firmament-3482$episode$102465$sub",
      "number": 9,
      "title": "Episode 9",
      "isFiller": false,
      "url": "https://aniwatch.to/watch/everlasting-immortal-firmament-3482?ep=102465"
    },
    {
      "id": "everlasting-immortal-firmament-3482$episode$102466$sub",
      "number": 10,
      "title": "Episode 10",
      "isFiller": false,
      "url": "https://aniwatch.to/watch/everlasting-immortal-firmament-3482?ep=102466"
    },
    {
      "id": "everlasting-immortal-firmament-3482$episode$102467$sub",
      "number": 11,
      "title": "Episode 11",
      "isFiller": false,
      "url": "https://aniwatch.to/watch/everlasting-immortal-firmament-3482?ep=102467"
    },
    {
      "id": "everlasting-immortal-firmament-3482$episode$102468$sub",
      "number": 12,
      "title": "Episode 12",
      "isFiller": false,
      "url": "https://aniwatch.to/watch/everlasting-immortal-firmament-3482?ep=102468"
    }
  ]
}