{
  "id": "yatterman-night-5713",
  "title": "Yatterman Night",
  "malID": 28155,
  "alID": 0,
  "image": "https://img.flawlessfiles.com/_r/300x400/100/08/cd/08cddc470a7dc2428b8c1df029f23b74/08cddc470a7dc2428b8c1df029f23b74.jpg",
  "description": "Several generations after the original Yatterman series, Leopard lives with her mother and guardians, Dorothy, Voltkatze, and Elephantus, just outside the prosperous Yatter Kingdom. She lives a happy if impoverished life, unaware of her ancestral ties to the infamous Doronbow Gang, until she discovers a mural of Doronjo, Boyacky, and Tonzura in a sealed off area of her home. It turns out that Dorothy, Voltkatze, and Elephantus are descendants of the villainous gangsters, which is why they have been forbidden from entering the hero Yatterman's Kingdom!\n\nAt first, Leopard vows to never engage in villainous actions like her ancestors, but new circumstances may mean that she must go back on her word, donning the identity of villain in search of true justice.",
  "type": "TV",
  "url": "https://aniwatch.to/yatterman-night-5713",
  "subOrDub": "sub",
  "hasSub": true,
  "totalEpisodes": 12,
  "episodes": [
    {
      "id": "yatterman-night-5713$episode$42297$sub",
      "number": 1,
      "title": "The World Is Pitch-Black",
      "isFiller": false,
      "url": "https://aniwatch.to/watch/yatterman-night-5713?ep=42297"
    },
    {
      "id": "yatterman-night-5713$episode$42298$sub",
      "number": 2,
      "title": "We'll Give Yatterman A Forehead Flicking",
      "isFiller": false,
      "url": "https://aniwatch.to/watch/yatterman-night-5713?ep=42298"
    },
    {
      "id": "yatterman-night-5713$episode$42299$sub",
      "number": 3,
      "title": "We’re Not Angels But We’ll Pretend to Be",
      "isFiller": false,
      "url": "https://aniwatch.to/watch/yatterman-night-5713?ep=42299"
    },
    {
      "id": "yatterman-night-5713$episode$42300$sub",
      "number": 4,
      "title": "Steamy Outdoor Hot Spring Trip",
      "isFiller": false,
      "url": "https://aniwatch.to/watch/yatterman-night-5713?ep=42300"
    },
    {
      "id": "yatterman-night-5713$episode$42301$sub",
      "number": 5,
      "title": "The Hurricane Dedicated to His Mother",
      "isFiller": false,
      "url": "https://aniwatch.to/watch/yatterman-night-5713?ep=42301"
    },
    {
      "id": "yatterman-night-5713$episode$42302$sub",
      "number": 6,
      "title": "The Flower That Blooms in Winter",
      "isFiller": false,
      "url": "https://aniwatch.to/watch/yatterman-night-5713?ep=42302"
    },
    {
      "id": "yatterman-night-5713$episode$42303$sub",
      "number": 7,
      "title": "Dream Sea",
      "isFiller": false,
      "url": "https://aniwatch.to/watch/yatterman-night-5713?ep=42303"
    },
    {
      "id": "yatterman-night-5713$episode$42304$sub",
      "number": 8,
      "title": "Kussie of Lake Kussharo-Dessharo",
      "isFiller": false,
      "url": "https://aniwatch.to/watch/yatterman-night-5713?ep=42304"
    },
    {
      "id": "yatterman-night-5713$episode$42305$sub",
      "number": 9,
      "title": "Abareshi Prison",
      "isFiller": false,
      "url": "https://aniwatch.to/watch/yatterman-night-5713?ep=42305"
    },
    {
      "id": "yatterman-night-5713$episode$42306$sub",
      "number": 10,
      "title": "The Twelve Yatter Guardian Gods’ Encirclement",
      "isFiller": false,
      "url": "https://aniwatch.to/watch/yatterman-night-5713?ep=42306"
    },
    {
      "id": "yatterman-night-5713$episode$42307$sub",
      "number": 11,
      "title": "The Truth About Yatter Metropolis",
      "isFiller": false,
      "url": "https://aniwatch.to/watch/yatterman-night-5713?ep=42307"
    },
    {
      "id": "yatterman-night-5713$episode$42308$sub",
      "number": 12,
      "title": "The Dawn",
      "isFiller": false,
      "url": "https://aniwatch.to/watch/yatterman-night-5713?ep=42308"
    }
  ]
}