[
  [
    {
      "name": "Vidstreaming",
      "url": "https://goone.pro/streaming.php?id=MTYxMDM5&title=Ajin+2nd+Season+%28Dub%29+Episode+1"
    },
    {
      "name": "Gogo server",
      "url": "https://goone.pro/embedplus?id=MTYxMDM5&token=vhTYmdHp84M3QxsTVBrIgg&expires=1697869762"
    },
    {
      "name": "Streamwish",
      "url": "https://awish.pro/e/l0je4l1z98no"
    },
    {
      "name": "Doodstream",
      "url": "https://dood.wf/e/a709byw1brz9"
    },
    {
      "name": "Filelions",
      "url": "https://alions.pro/v/6js4rmrgkgsu"
    }
  ],
  [
    {
      "name": "Vidstreaming",
      "url": "https://goone.pro/streaming.php?id=MTYxMDQw&title=Ajin+2nd+Season+%28Dub%29+Episode+2"
    },
    {
      "name": "Gogo server",
      "url": "https://goone.pro/embedplus?id=MTYxMDQw&token=fZMILhjxT-a7FrNC5ZkQlQ&expires=1697869762"
    },
    {
      "name": "Streamwish",
      "url": "https://awish.pro/e/cca9q7yrasfy"
    },
    {
      "name": "Doodstream",
      "url": "https://dood.wf/e/ddx4yeq8p07a"
    },
    {
      "name": "Filelions",
      "url": "https://alions.pro/v/y5qwubwwd7ga"
    }
  ],
  [
    {
      "name": "Vidstreaming",
      "url": "https://goone.pro/streaming.php?id=MTYxMDQx&title=Ajin+2nd+Season+%28Dub%29+Episode+3"
    },
    {
      "name": "Gogo server",
      "url": "https://goone.pro/embedplus?id=MTYxMDQx&token=duG0YndnMyw_W_d1A8TTvQ&expires=1697869762"
    },
    {
      "name": "Streamwish",
      "url": "https://awish.pro/e/jdag3u4nyc5o"
    },
    {
      "name": "Mixdrop",
      "url": "https://mixdrop.co/e/pkeqqlm6hvvll7"
    },
    {
      "name": "Doodstream",
      "url": "https://dood.wf/e/8efdlxoj98oo"
    },
    {
      "name": "Filelions",
      "url": "https://alions.pro/v/82e8nbz21qq9"
    }
  ],
  [
    {
      "name": "Vidstreaming",
      "url": "https://goone.pro/streaming.php?id=MTYxMDQy&title=Ajin+2nd+Season+%28Dub%29+Episode+4"
    },
    {
      "name": "Gogo server",
      "url": "https://goone.pro/embedplus?id=MTYxMDQy&token=x_UOZJZM932_AoWpPXWY3A&expires=1697869762"
    },
    {
      "name": "Streamwish",
      "url": "https://awish.pro/e/qijbxtjw6vrz"
    },
    {
      "name": "Doodstream",
      "url": "https://dood.wf/e/llek9fvr076j"
    },
    {
      "name": "Filelions",
      "url": "https://alions.pro/v/viqhh6prhgab"
    }
  ],
  [
    {
      "name": "Vidstreaming",
      "url": "https://goone.pro/streaming.php?id=MTYxMDQz&title=Ajin+2nd+Season+%28Dub%29+Episode+5"
    },
    {
      "name": "Gogo server",
      "url": "https://goone.pro/embedplus?id=MTYxMDQz&token=SiOLBm6avYaS7KAJKItY_g&expires=1697869762"
    },
    {
      "name": "Streamwish",
      "url": "https://awish.pro/e/p3f47q1s6c1o"
    },
    {
      "name": "Mixdrop",
      "url": "https://mixdrop.co/e/vnerr4rktvq40z"
    },
    {
      "name": "Doodstream",
      "url": "https://dood.wf/e/145u2pwqa0f7"
    },
    {
      "name": "Filelions",
      "url": "https://alions.pro/v/ylvoga247uxh"
    }
  ],
  [
    {
      "name": "Vidstreaming",
      "url": "https://goone.pro/streaming.php?id=MTYxMDQ0&title=Ajin+2nd+Season+%28Dub%29+Episode+6"
    },
    {
      "name": "Gogo server",
      "url": "https://goone.pro/embedplus?id=MTYxMDQ0&token=EQiQA_nF8e61SQpqdjf6HA&expires=1697869762"
    },
    {
      "name": "Streamwish",
      "url": "https://awish.pro/e/do4tda0dogt6"
    },
    {
      "name": "Mixdrop",
      "url": "https://mixdrop.co/e/gnlxx7nkhwdd6j"
    },
    {
      "name": "Doodstream",
      "url": "https://dood.wf/e/69ykbxrnznrb"
    },
    {
      "name": "Filelions",
      "url": "https://alions.pro/v/rupped1otjbp"
    }
  ],
  [
    {
      "name": "Vidstreaming",
      "url": "https://goone.pro/streaming.php?id=MTYxMDQ1&title=Ajin+2nd+Season+%28Dub%29+Episode+7"
    },
    {
      "name": "Gogo server",
      "url": "https://goone.pro/embedplus?id=MTYxMDQ1&token=3D4P7AkqhanQgk4CiCfSGQ&expires=1697869762"
    },
    {
      "name": "Streamwish",
      "url": "https://awish.pro/e/7n5gwanri4aq"
    },
    {
      "name": "Mixdrop",
      "url": "https://mixdrop.co/e/dq0ww61nhxjmoj"
    },
    {
      "name": "Doodstream",
      "url": "https://dood.wf/e/rjggnbha4w6h"
    },
    {
      "name": "Filelions",
      "url": "https://alions.pro/v/6c1oe4eqxhnv"
    }
  ],
  [
    {
      "name": "Vidstreaming",
      "url": "https://goone.pro/streaming.php?id=MTYxMDQ2&title=Ajin+2nd+Season+%28Dub%29+Episode+8"
    },
    {
      "name": "Gogo server",
      "url": "https://goone.pro/embedplus?id=MTYxMDQ2&token=umNQ1h69adAOu6ALN6kULQ&expires=1697869762"
    },
    {
      "name": "Streamwish",
      "url": "https://awish.pro/e/0tvqqfb8weda"
    },
    {
      "name": "Mixdrop",
      "url": "https://mixdrop.co/e/wnerrgjmtv17w7"
    },
    {
      "name": "Doodstream",
      "url": "https://dood.wf/e/eq5b362cgbbt"
    },
    {
      "name": "Filelions",
      "url": "https://alions.pro/v/si3ssni3ir9y"
    }
  ],
  [
    {
      "name": "Vidstreaming",
      "url": "https://goone.pro/streaming.php?id=MTYxMDQ3&title=Ajin+2nd+Season+%28Dub%29+Episode+9"
    },
    {
      "name": "Gogo server",
      "url": "https://goone.pro/embedplus?id=MTYxMDQ3&token=ZKCSwX07SZIUU825snTusw&expires=1697869762"
    },
    {
      "name": "Streamwish",
      "url": "https://awish.pro/e/j3qlc0qfkcfx"
    },
    {
      "name": "Doodstream",
      "url": "https://dood.wf/e/l3md9xm5z5gr"
    },
    {
      "name": "Filelions",
      "url": "https://alions.pro/v/p3szid5q16gd"
    }
  ],
  [
    {
      "name": "Vidstreaming",
      "url": "https://goone.pro/streaming.php?id=MTYxMDQ4&title=Ajin+2nd+Season+%28Dub%29+Episode+10"
    },
    {
      "name": "Gogo server",
      "url": "https://goone.pro/embedplus?id=MTYxMDQ4&token=dLGvMgiUqWNHtpV67iU4Hw&expires=1697869762"
    },
    {
      "name": "Streamwish",
      "url": "https://awish.pro/e/ebz2ef5ibth1"
    },
    {
      "name": "Doodstream",
      "url": "https://dood.wf/e/87hr9c6lm2hk"
    },
    {
      "name": "Filelions",
      "url": "https://alions.pro/v/0bms65hwfbtf"
    }
  ],
  [
    {
      "name": "Vidstreaming",
      "url": "https://goone.pro/streaming.php?id=MTYxMDQ5&title=Ajin+2nd+Season+%28Dub%29+Episode+11"
    },
    {
      "name": "Gogo server",
      "url": "https://goone.pro/embedplus?id=MTYxMDQ5&token=FBV1FC5uooYUopTv7MOARA&expires=1697869762"
    },
    {
      "name": "Streamwish",
      "url": "https://awish.pro/e/zva9s1p6ii0v"
    },
    {
      "name": "Doodstream",
      "url": "https://dood.wf/e/lxxpzml7srag"
    },
    {
      "name": "Filelions",
      "url": "https://alions.pro/v/53q6o9ihx492"
    }
  ],
  [
    {
      "name": "Vidstreaming",
      "url": "https://goone.pro/streaming.php?id=MTYxMDUw&title=Ajin+2nd+Season+%28Dub%29+Episode+12"
    },
    {
      "name": "Gogo server",
      "url": "https://goone.pro/embedplus?id=MTYxMDUw&token=Fds7YU3bZx0MqPU2N13hbA&expires=1697869762"
    },
    {
      "name": "Streamwish",
      "url": "https://awish.pro/e/5kmd8kgtau3r"
    },
    {
      "name": "Doodstream",
      "url": "https://dood.wf/e/urngdsk6uxz6"
    },
    {
      "name": "Filelions",
      "url": "https://alions.pro/v/yrrw0x8v2bru"
    }
  ],
  [
    {
      "name": "Vidstreaming",
      "url": "https://goone.pro/streaming.php?id=MTYxMDUx&title=Ajin+2nd+Season+%28Dub%29+Episode+13"
    },
    {
      "name": "Gogo server",
      "url": "https://goone.pro/embedplus?id=MTYxMDUx&token=lHOeoivTPJ_cW8JZSRj_wQ&expires=1697869762"
    },
    {
      "name": "Streamwish",
      "url": "https://awish.pro/e/r90s9guiav4i"
    },
    {
      "name": "Doodstream",
      "url": "https://dood.wf/e/ovigk51g56is"
    },
    {
      "name": "Filelions",
      "url": "https://alions.pro/v/6a3i7jqvzlg1"
    }
  ]
]