[
  [
    {
      "name": "Vidstreaming",
      "url": "https://goone.pro/streaming.php?id=MzI1MTI=&title=Kujibiki+Unbalance+Episode+1"
    },
    {
      "name": "Gogo server",
      "url": "https://goone.pro/embedplus?id=MzI1MTI=&token=NI1N85I-DZJBW1pZf0vNMw&expires=1697893551"
    },
    {
      "name": "Streamwish",
      "url": "https://awish.pro/e/5vo78zjxzq2l"
    },
    {
      "name": "Server Hydrax",
      "url": "https://hydrax.net/watch?v=8AOuW-Dkd4"
    },
    {
      "name": "Mp4Upload",
      "url": "https://www.mp4upload.com/embed-amn453gqjex7.html"
    },
    {
      "name": "Doodstream",
      "url": "https://dood.wf/e/psy9fozrx876"
    },
    {
      "name": "Filelions",
      "url": "https://alions.pro/v/br483v45ggv4"
    }
  ],
  [
    {
      "name": "Vidstreaming",
      "url": "https://goone.pro/streaming.php?id=MzI1MTM=&title=Kujibiki+Unbalance+Episode+2"
    },
    {
      "name": "Gogo server",
      "url": "https://goone.pro/embedplus?id=MzI1MTM=&token=LE41MGYGXAyKnExogH4Uhg&expires=1697893551"
    },
    {
      "name": "Streamwish",
      "url": "https://awish.pro/e/vpnwh8b66sr6"
    },
    {
      "name": "Server Hydrax",
      "url": "https://hydrax.net/watch?v=1fzv-DaoC"
    },
    {
      "name": "Mp4Upload",
      "url": "https://www.mp4upload.com/embed-h400ziuaxr6w.html"
    },
    {
      "name": "Doodstream",
      "url": "https://dood.wf/e/mxoxadvuuvfo"
    },
    {
      "name": "Filelions",
      "url": "https://alions.pro/v/3x3g9ckyfhzp"
    }
  ],
  [
    {
      "name": "Vidstreaming",
      "url": "https://goone.pro/streaming.php?id=MzI1MTQ=&title=Kujibiki+Unbalance+Episode+3"
    },
    {
      "name": "Gogo server",
      "url": "https://goone.pro/embedplus?id=MzI1MTQ=&token=3NI0tZGZMgeTL_pbmOcGkA&expires=1697893551"
    },
    {
      "name": "Streamwish",
      "url": "https://awish.pro/e/a72glrjhjcww"
    },
    {
      "name": "Server Hydrax",
      "url": "https://hydrax.net/watch?v=Ouy4D8YAg"
    },
    {
      "name": "Mp4Upload",
      "url": "https://www.mp4upload.com/embed-zu45vk7hmwo1.html"
    },
    {
      "name": "Doodstream",
      "url": "https://dood.wf/e/jow66cajvlf9"
    },
    {
      "name": "Filelions",
      "url": "https://alions.pro/v/ylva62avubnp"
    }
  ],
  [
    {
      "name": "Vidstreaming",
      "url": "https://goone.pro/streaming.php?id=MzI1MjE=&title=Kujibiki+Unbalance+Episode+4"
    },
    {
      "name": "Gogo server",
      "url": "https://goone.pro/embedplus?id=MzI1MjE=&token=pqGjS80E3tIXtrydYyMW7g&expires=1697893551"
    },
    {
      "name": "Streamwish",
      "url": "https://awish.pro/e/0uljbvej78fc"
    },
    {
      "name": "Server Hydrax",
      "url": "https://hydrax.net/watch?v=CjeJnzg5qQ"
    },
    {
      "name": "Mp4Upload",
      "url": "https://www.mp4upload.com/embed-zwo8ywiwjv1m.html"
    },
    {
      "name": "Doodstream",
      "url": "https://dood.wf/e/eaoauasq7dgz"
    },
    {
      "name": "Filelions",
      "url": "https://alions.pro/v/x67lt53ciefb"
    }
  ],
  [
    {
      "name": "Vidstreaming",
      "url": "https://goone.pro/streaming.php?id=MzI1MjQ=&title=Kujibiki+Unbalance+Episode+5"
    },
    {
      "name": "Gogo server",
      "url": "https://goone.pro/embedplus?id=MzI1MjQ=&token=hn1fo-2yfViE7CKn4k7toQ&expires=1697893551"
    },
    {
      "name": "Streamwish",
      "url": "https://awish.pro/e/gec8p9ncmzu7"
    },
    {
      "name": "Server Hydrax",
      "url": "https://hydrax.net/watch?v=YXIizrBX7"
    },
    {
      "name": "Mp4Upload",
      "url": "https://www.mp4upload.com/embed-uo26lsg4osgi.html"
    },
    {
      "name": "Doodstream",
      "url": "https://dood.wf/e/7ymur04981ew"
    },
    {
      "name": "Filelions",
      "url": "https://alions.pro/v/rc1vgq004vwg"
    }
  ],
  [
    {
      "name": "Vidstreaming",
      "url": "https://goone.pro/streaming.php?id=MzI1MjU=&title=Kujibiki+Unbalance+Episode+6"
    },
    {
      "name": "Gogo server",
      "url": "https://goone.pro/embedplus?id=MzI1MjU=&token=GjnL5DawudZ-0892laANEg&expires=1697893551"
    },
    {
      "name": "Streamwish",
      "url": "https://awish.pro/e/s7kxk0lkli5s"
    },
    {
      "name": "Server Hydrax",
      "url": "https://hydrax.net/watch?v=5ZgsKDeEl"
    },
    {
      "name": "Mp4Upload",
      "url": "https://www.mp4upload.com/embed-3zyg7jvvs6wu.html"
    },
    {
      "name": "Doodstream",
      "url": "https://dood.wf/e/5luzejbit2pp"
    },
    {
      "name": "Filelions",
      "url": "https://alions.pro/v/5ysd003cydwm"
    }
  ],
  [
    {
      "name": "Vidstreaming",
      "url": "https://goone.pro/streaming.php?id=MzI1NTQ=&title=Kujibiki+Unbalance+Episode+7"
    },
    {
      "name": "Gogo server",
      "url": "https://goone.pro/embedplus?id=MzI1NTQ=&token=FV_mxbRoDDzLbzbBZ9gpoA&expires=1697893551"
    },
    {
      "name": "Streamwish",
      "url": "https://awish.pro/e/gp11r2lo5b3r"
    },
    {
      "name": "Server Hydrax",
      "url": "https://hydrax.net/watch?v=FcdBDu9Bk"
    },
    {
      "name": "Mp4Upload",
      "url": "https://www.mp4upload.com/embed-28kph8a80fde.html"
    },
    {
      "name": "Doodstream",
      "url": "https://dood.wf/e/g3mfkipf95c0"
    },
    {
      "name": "Filelions",
      "url": "https://alions.pro/v/a1e32izih2qk"
    }
  ],
  [
    {
      "name": "Vidstreaming",
      "url": "https://goone.pro/streaming.php?id=MzI1NTk=&title=Kujibiki+Unbalance+Episode+8"
    },
    {
      "name": "Gogo server",
      "url": "https://goone.pro/embedplus?id=MzI1NTk=&token=rTU4J9KlpV26eAx7_y_wHA&expires=1697893551"
    },
    {
      "name": "Streamwish",
      "url": "https://awish.pro/e/c63hqjl550qo"
    },
    {
      "name": "Server Hydrax",
      "url": "https://hydrax.net/watch?v=UVAvCWK3D"
    },
    {
      "name": "Mp4Upload",
      "url": "https://www.mp4upload.com/embed-6s6v2bleajz3.html"
    },
    {
      "name": "Doodstream",
      "url": "https://dood.wf/e/dhwbr3ws05tl"
    },
    {
      "name": "Filelions",
      "url": "https://alions.pro/v/ygdvl04lycvh"
    }
  ],
  [
    {
      "name": "Vidstreaming",
      "url": "https://goone.pro/streaming.php?id=MzI1NjE=&title=Kujibiki+Unbalance+Episode+9"
    },
    {
      "name": "Gogo server",
      "url": "https://goone.pro/embedplus?id=MzI1NjE=&token=d1D4BoG-DWMMZUAgDbEUFQ&expires=1697893551"
    },
    {
      "name": "Streamwish",
      "url": "https://awish.pro/e/gvbskzazqq1f"
    },
    {
      "name": "Server Hydrax",
      "url": "https://hydrax.net/watch?v=zSA9YjNrr2"
    },
    {
      "name": "Mp4Upload",
      "url": "https://www.mp4upload.com/embed-88k1eztq9dh7.html"
    },
    {
      "name": "Doodstream",
      "url": "https://dood.wf/e/fw0hvz1etdiz"
    },
    {
      "name": "Filelions",
      "url": "https://alions.pro/v/zcf40pskwf2w"
    }
  ],
  [
    {
      "name": "Vidstreaming",
      "url": "https://goone.pro/streaming.php?id=MzI1Njk=&title=Kujibiki+Unbalance+Episode+10"
    },
    {
      "name": "Gogo server",
      "url": "https://goone.pro/embedplus?id=MzI1Njk=&token=hYnwc3Qaz58aVvfdQeVleA&expires=1697893551"
    },
    {
      "name": "Streamwish",
      "url": "https://awish.pro/e/i23wlan603jr"
    },
    {
      "name": "Server Hydrax",
      "url": "https://hydrax.net/watch?v=I7ofvOvrXpj"
    },
    {
      "name": "Mp4Upload",
      "url": "https://www.mp4upload.com/embed-d4obj7l3mile.html"
    },
    {
      "name": "Doodstream",
      "url": "https://dood.wf/e/e7x6jwi0diy1"
    },
    {
      "name": "Filelions",
      "url": "https://alions.pro/v/9h5lrjusvun8"
    }
  ],
  [
    {
      "name": "Vidstreaming",
      "url": "https://goone.pro/streaming.php?id=MzI1NzM=&title=Kujibiki+Unbalance+Episode+11"
    },
    {
      "name": "Gogo server",
      "url": "https://goone.pro/embedplus?id=MzI1NzM=&token=ilOaWw-auYeLVolbp82AZA&expires=1697893551"
    },
    {
      "name": "Streamwish",
      "url": "https://awish.pro/e/lizi6b9yq0v0"
    },
    {
      "name": "Server Hydrax",
      "url": "https://hydrax.net/watch?v=m2qhK3uFMY"
    },
    {
      "name": "Mp4Upload",
      "url": "https://www.mp4upload.com/embed-owj9fzoepz0o.html"
    },
    {
      "name": "Doodstream",
      "url": "https://dood.wf/e/p830pkjvnjs3"
    },
    {
      "name": "Filelions",
      "url": "https://alions.pro/v/zkepbw6h7m8z"
    }
  ],
  [
    {
      "name": "Vidstreaming",
      "url": "https://goone.pro/streaming.php?id=MzI1NzQ=&title=Kujibiki+Unbalance+Episode+12"
    },
    {
      "name": "Gogo server",
      "url": "https://goone.pro/embedplus?id=MzI1NzQ=&token=0ZIQjKIa2mi029diaZoHtQ&expires=1697893551"
    },
    {
      "name": "Streamwish",
      "url": "https://awish.pro/e/ouawcyo64694"
    },
    {
      "name": "Server Hydrax",
      "url": "https://hydrax.net/watch?v=SyguI8atms"
    },
    {
      "name": "Mp4Upload",
      "url": "https://www.mp4upload.com/embed-wqoqhnwj7axr.html"
    },
    {
      "name": "Doodstream",
      "url": "https://dood.wf/e/8f97tdbh7wvi"
    },
    {
      "name": "Filelions",
      "url": "https://alions.pro/v/167s0wf51f6w"
    }
  ]
]