[
  [
    {
      "name": "Vidstreaming",
      "url": "https://goone.pro/streaming.php?id=MTI4OTAw&title=Onegai+My+Melody%3A+Kuru+Kuru+Shuffle%21+Episode+1"
    },
    {
      "name": "Gogo server",
      "url": "https://goone.pro/embedplus?id=MTI4OTAw&token=gpVeYVS-y60wywFnwnLbfg&expires=1697897203"
    },
    {
      "name": "Streamwish",
      "url": "https://awish.pro/e/abdwne6bjkkj"
    },
    {
      "name": "Server Hydrax",
      "url": "https://hydrax.net/watch?v=6zcQK2ZuM"
    },
    {
      "name": "Mp4Upload",
      "url": "https://www.mp4upload.com/embed-s93e4rkyes1v.html"
    },
    {
      "name": "Doodstream",
      "url": "https://dood.wf/e/br5nd02tql5b"
    },
    {
      "name": "Filelions",
      "url": "https://alions.pro/v/8fcy7o8mozlx"
    }
  ],
  [
    {
      "name": "Vidstreaming",
      "url": "https://goone.pro/streaming.php?id=MTI4OTAx&title=Onegai+My+Melody%3A+Kuru+Kuru+Shuffle%21+Episode+2"
    },
    {
      "name": "Gogo server",
      "url": "https://goone.pro/embedplus?id=MTI4OTAx&token=V7PkBXN8MYCTfixtw07jMA&expires=1697897203"
    },
    {
      "name": "Streamwish",
      "url": "https://awish.pro/e/5t2ujkrujokl"
    },
    {
      "name": "Server Hydrax",
      "url": "https://hydrax.net/watch?v=NETTndjbQ"
    },
    {
      "name": "Mp4Upload",
      "url": "https://www.mp4upload.com/embed-dav5rdf7vytf.html"
    },
    {
      "name": "Doodstream",
      "url": "https://dood.wf/e/0if8bezm7cme"
    },
    {
      "name": "Filelions",
      "url": "https://alions.pro/v/rvis8m076elc"
    }
  ],
  [
    {
      "name": "Vidstreaming",
      "url": "https://goone.pro/streaming.php?id=MTI4OTAy&title=Onegai+My+Melody%3A+Kuru+Kuru+Shuffle%21+Episode+3"
    },
    {
      "name": "Gogo server",
      "url": "https://goone.pro/embedplus?id=MTI4OTAy&token=b-ZkUB5TedUIEocMM4XVOw&expires=1697897203"
    },
    {
      "name": "Streamwish",
      "url": "https://awish.pro/e/x2l5behquu0c"
    },
    {
      "name": "Server Hydrax",
      "url": "https://hydrax.net/watch?v=Rc48QKSvP1"
    },
    {
      "name": "Mp4Upload",
      "url": "https://www.mp4upload.com/embed-ggcg4ig5dx6n.html"
    },
    {
      "name": "Doodstream",
      "url": "https://dood.wf/e/rhwa2qpqu99s"
    },
    {
      "name": "Filelions",
      "url": "https://alions.pro/v/iyg7roe1w2z1"
    }
  ],
  [
    {
      "name": "Vidstreaming",
      "url": "https://goone.pro/streaming.php?id=MTI4OTAz&title=Onegai+My+Melody%3A+Kuru+Kuru+Shuffle%21+Episode+4"
    },
    {
      "name": "Gogo server",
      "url": "https://goone.pro/embedplus?id=MTI4OTAz&token=ncwK6tVAo8YR9PyzylaGdA&expires=1697897203"
    },
    {
      "name": "Streamwish",
      "url": "https://awish.pro/e/m9kubz7uc6rd"
    },
    {
      "name": "Server Hydrax",
      "url": "https://hydrax.net/watch?v=7O4AqoFKZ"
    },
    {
      "name": "Mp4Upload",
      "url": "https://www.mp4upload.com/embed-ng0hsytcc4d1.html"
    },
    {
      "name": "Doodstream",
      "url": "https://dood.wf/e/7qofj255iuo9"
    },
    {
      "name": "Filelions",
      "url": "https://alions.pro/v/5pxh3v83rviy"
    }
  ],
  [
    {
      "name": "Vidstreaming",
      "url": "https://goone.pro/streaming.php?id=MTI4OTA0&title=Onegai+My+Melody%3A+Kuru+Kuru+Shuffle%21+Episode+5"
    },
    {
      "name": "Gogo server",
      "url": "https://goone.pro/embedplus?id=MTI4OTA0&token=RCojyvTVIZrnAxy4HJqkXg&expires=1697897203"
    },
    {
      "name": "Streamwish",
      "url": "https://awish.pro/e/8j5mvs1w1ssk"
    },
    {
      "name": "Server Hydrax",
      "url": "https://hydrax.net/watch?v=6cWV3--0fU"
    },
    {
      "name": "Mp4Upload",
      "url": "https://www.mp4upload.com/embed-lr8740llpkk8.html"
    },
    {
      "name": "Doodstream",
      "url": "https://dood.wf/e/3zc94iwvnhj9"
    },
    {
      "name": "Filelions",
      "url": "https://alions.pro/v/mud244ncn01o"
    }
  ],
  [
    {
      "name": "Vidstreaming",
      "url": "https://goone.pro/streaming.php?id=MTI4OTA1&title=Onegai+My+Melody%3A+Kuru+Kuru+Shuffle%21+Episode+6"
    },
    {
      "name": "Gogo server",
      "url": "https://goone.pro/embedplus?id=MTI4OTA1&token=ZWDBQ8GwzUWPJWD1aQ_lbw&expires=1697897203"
    },
    {
      "name": "Streamwish",
      "url": "https://awish.pro/e/hbcclv799j8m"
    },
    {
      "name": "Server Hydrax",
      "url": "https://hydrax.net/watch?v=DXV9G-nj8T"
    },
    {
      "name": "Mp4Upload",
      "url": "https://www.mp4upload.com/embed-slt26ktq6gl9.html"
    },
    {
      "name": "Doodstream",
      "url": "https://dood.wf/e/za7ws0cptxdf"
    },
    {
      "name": "Filelions",
      "url": "https://alions.pro/v/849l17chr5e5"
    }
  ],
  [
    {
      "name": "Vidstreaming",
      "url": "https://goone.pro/streaming.php?id=MTI4OTA2&title=Onegai+My+Melody%3A+Kuru+Kuru+Shuffle%21+Episode+7"
    },
    {
      "name": "Gogo server",
      "url": "https://goone.pro/embedplus?id=MTI4OTA2&token=uqU8aWafaTTQKiR7ZYqWRg&expires=1697897203"
    },
    {
      "name": "Streamwish",
      "url": "https://awish.pro/e/zeqz0uxdrijl"
    },
    {
      "name": "Server Hydrax",
      "url": "https://hydrax.net/watch?v=8i2OJALdn3"
    },
    {
      "name": "Mp4Upload",
      "url": "https://www.mp4upload.com/embed-uun4tup3jiit.html"
    },
    {
      "name": "Doodstream",
      "url": "https://dood.wf/e/arltnt73s2rj"
    },
    {
      "name": "Filelions",
      "url": "https://alions.pro/v/vui9m8xj33z7"
    }
  ],
  [
    {
      "name": "Vidstreaming",
      "url": "https://goone.pro/streaming.php?id=MTI4OTA3&title=Onegai+My+Melody%3A+Kuru+Kuru+Shuffle%21+Episode+8"
    },
    {
      "name": "Gogo server",
      "url": "https://goone.pro/embedplus?id=MTI4OTA3&token=SYu_ItvkqJUl-WeG8_ebeg&expires=1697897203"
    },
    {
      "name": "Streamwish",
      "url": "https://awish.pro/e/mmna7o88ksqk"
    },
    {
      "name": "Server Hydrax",
      "url": "https://hydrax.net/watch?v=JdeXGelEqg"
    },
    {
      "name": "Mp4Upload",
      "url": "https://www.mp4upload.com/embed-e0dem9kkjnzq.html"
    },
    {
      "name": "Doodstream",
      "url": "https://dood.wf/e/9ri95woxa0g0"
    },
    {
      "name": "Filelions",
      "url": "https://alions.pro/v/ajdoydtxh1va"
    }
  ],
  [
    {
      "name": "Vidstreaming",
      "url": "https://goone.pro/streaming.php?id=MTI4OTA4&title=Onegai+My+Melody%3A+Kuru+Kuru+Shuffle%21+Episode+9"
    },
    {
      "name": "Gogo server",
      "url": "https://goone.pro/embedplus?id=MTI4OTA4&token=VqVqv5HITtodZcmOggvclQ&expires=1697897203"
    },
    {
      "name": "Streamwish",
      "url": "https://awish.pro/e/e5coy85iz9zf"
    },
    {
      "name": "Server Hydrax",
      "url": "https://hydrax.net/watch?v=GkHKhHqKf0"
    },
    {
      "name": "Mp4Upload",
      "url": "https://www.mp4upload.com/embed-shendyqvgzxn.html"
    },
    {
      "name": "Doodstream",
      "url": "https://dood.wf/e/f142uy2kldf5"
    },
    {
      "name": "Filelions",
      "url": "https://alions.pro/v/qaugaorzgbhr"
    }
  ],
  [
    {
      "name": "Vidstreaming",
      "url": "https://goone.pro/streaming.php?id=MTI4OTA5&title=Onegai+My+Melody%3A+Kuru+Kuru+Shuffle%21+Episode+10"
    },
    {
      "name": "Gogo server",
      "url": "https://goone.pro/embedplus?id=MTI4OTA5&token=ohIiqdpHmIqeyE-1R3E3og&expires=1697897203"
    },
    {
      "name": "Streamwish",
      "url": "https://awish.pro/e/gf9za55lztnv"
    },
    {
      "name": "Server Hydrax",
      "url": "https://hydrax.net/watch?v=6NntkO2ZYj"
    },
    {
      "name": "Mp4Upload",
      "url": "https://www.mp4upload.com/embed-q8omsy8y02as.html"
    },
    {
      "name": "Doodstream",
      "url": "https://dood.wf/e/a55t3z1yfi9f"
    },
    {
      "name": "Filelions",
      "url": "https://alions.pro/v/2utejqo72u8x"
    }
  ],
  [
    {
      "name": "Vidstreaming",
      "url": "https://goone.pro/streaming.php?id=MTI4OTEw&title=Onegai+My+Melody%3A+Kuru+Kuru+Shuffle%21+Episode+11"
    },
    {
      "name": "Gogo server",
      "url": "https://goone.pro/embedplus?id=MTI4OTEw&token=h9cwH4lT-zKHE7Fo9nOz7Q&expires=1697897203"
    },
    {
      "name": "Streamwish",
      "url": "https://awish.pro/e/hd3siogzg8gy"
    },
    {
      "name": "Server Hydrax",
      "url": "https://hydrax.net/watch?v=5SKiHOKi7"
    },
    {
      "name": "Mp4Upload",
      "url": "https://www.mp4upload.com/embed-dwspi7w22pp4.html"
    },
    {
      "name": "Doodstream",
      "url": "https://dood.wf/e/ccbob1hbqn20"
    },
    {
      "name": "Filelions",
      "url": "https://alions.pro/v/8sywq7riuaza"
    }
  ],
  [
    {
      "name": "Vidstreaming",
      "url": "https://goone.pro/streaming.php?id=MTI4OTEx&title=Onegai+My+Melody%3A+Kuru+Kuru+Shuffle%21+Episode+12"
    },
    {
      "name": "Gogo server",
      "url": "https://goone.pro/embedplus?id=MTI4OTEx&token=iinzvxZgKkKJWeH1QlcQMA&expires=1697897203"
    },
    {
      "name": "Streamwish",
      "url": "https://awish.pro/e/27rtd45d44ob"
    },
    {
      "name": "Server Hydrax",
      "url": "https://hydrax.net/watch?v=uFlS_4vqm"
    },
    {
      "name": "Mp4Upload",
      "url": "https://www.mp4upload.com/embed-7ubc7h1fagaj.html"
    },
    {
      "name": "Doodstream",
      "url": "https://dood.wf/e/2qaik8lrry0v"
    },
    {
      "name": "Filelions",
      "url": "https://alions.pro/v/wmarn1b1yfts"
    }
  ],
  [
    {
      "name": "Vidstreaming",
      "url": "https://goone.pro/streaming.php?id=MTI4OTEy&title=Onegai+My+Melody%3A+Kuru+Kuru+Shuffle%21+Episode+13"
    },
    {
      "name": "Gogo server",
      "url": "https://goone.pro/embedplus?id=MTI4OTEy&token=8E1zs1E_Cj0vxi3mvnRkWA&expires=1697897203"
    },
    {
      "name": "Streamwish",
      "url": "https://awish.pro/e/qi1ed722uy52"
    },
    {
      "name": "Server Hydrax",
      "url": "https://hydrax.net/watch?v=qXYEHp6cqv"
    },
    {
      "name": "Mp4Upload",
      "url": "https://www.mp4upload.com/embed-utspcidn6a2d.html"
    },
    {
      "name": "Doodstream",
      "url": "https://dood.wf/e/cf68qcmtaaq4"
    },
    {
      "name": "Filelions",
      "url": "https://alions.pro/v/swwtigxzghie"
    }
  ],
  [
    {
      "name": "Vidstreaming",
      "url": "https://goone.pro/streaming.php?id=MTI4OTEz&title=Onegai+My+Melody%3A+Kuru+Kuru+Shuffle%21+Episode+14"
    },
    {
      "name": "Gogo server",
      "url": "https://goone.pro/embedplus?id=MTI4OTEz&token=HXr8jxrqK2itBRL4Y2ucig&expires=1697897203"
    },
    {
      "name": "Streamwish",
      "url": "https://awish.pro/e/mqbhjlz0xvek"
    },
    {
      "name": "Server Hydrax",
      "url": "https://hydrax.net/watch?v=g-8_5HJIu"
    },
    {
      "name": "Mp4Upload",
      "url": "https://www.mp4upload.com/embed-sc500x3paogm.html"
    },
    {
      "name": "Doodstream",
      "url": "https://dood.wf/e/9tuxnedpjm9h"
    },
    {
      "name": "Filelions",
      "url": "https://alions.pro/v/ec8y70ne8lqk"
    }
  ],
  [
    {
      "name": "Vidstreaming",
      "url": "https://goone.pro/streaming.php?id=MTI4OTE0&title=Onegai+My+Melody%3A+Kuru+Kuru+Shuffle%21+Episode+15"
    },
    {
      "name": "Gogo server",
      "url": "https://goone.pro/embedplus?id=MTI4OTE0&token=KVqiGtBGK_jLrrbxFMfVqQ&expires=1697897203"
    },
    {
      "name": "Streamwish",
      "url": "https://awish.pro/e/94fsf1w9mqz5"
    },
    {
      "name": "Server Hydrax",
      "url": "https://hydrax.net/watch?v=tHeye7VIl"
    },
    {
      "name": "Mp4Upload",
      "url": "https://www.mp4upload.com/embed-pdkzr71qysnp.html"
    },
    {
      "name": "Doodstream",
      "url": "https://dood.wf/e/k6srjw4wofd8"
    },
    {
      "name": "Filelions",
      "url": "https://alions.pro/v/u9m8af9yr9x8"
    }
  ],
  [
    {
      "name": "Vidstreaming",
      "url": "https://goone.pro/streaming.php?id=MTI4OTE1&title=Onegai+My+Melody%3A+Kuru+Kuru+Shuffle%21+Episode+16"
    },
    {
      "name": "Gogo server",
      "url": "https://goone.pro/embedplus?id=MTI4OTE1&token=y7NrO5bynVP1HFkOcXt7qA&expires=1697897203"
    },
    {
      "name": "Streamwish",
      "url": "https://awish.pro/e/gmb6pkotrv9z"
    },
    {
      "name": "Server Hydrax",
      "url": "https://hydrax.net/watch?v=a2DS9p2YR8"
    },
    {
      "name": "Mp4Upload",
      "url": "https://www.mp4upload.com/embed-sby003cmpx0y.html"
    },
    {
      "name": "Doodstream",
      "url": "https://dood.wf/e/ct2j697n6ii7"
    },
    {
      "name": "Filelions",
      "url": "https://alions.pro/v/59ajlzsr2zqr"
    }
  ],
  [
    {
      "name": "Vidstreaming",
      "url": "https://goone.pro/streaming.php?id=MTI4OTE2&title=Onegai+My+Melody%3A+Kuru+Kuru+Shuffle%21+Episode+17"
    },
    {
      "name": "Gogo server",
      "url": "https://goone.pro/embedplus?id=MTI4OTE2&token=eCCBY6Hn6WHUWHEFcyN4AQ&expires=1697897203"
    },
    {
      "name": "Streamwish",
      "url": "https://awish.pro/e/gpdvo0e73imd"
    },
    {
      "name": "Server Hydrax",
      "url": "https://hydrax.net/watch?v=bbG7ajR2o"
    },
    {
      "name": "Mp4Upload",
      "url": "https://www.mp4upload.com/embed-97856397sc40.html"
    },
    {
      "name": "Doodstream",
      "url": "https://dood.wf/e/8irzq44ijqni"
    },
    {
      "name": "Filelions",
      "url": "https://alions.pro/v/8jiax3vo0zg5"
    }
  ],
  [
    {
      "name": "Vidstreaming",
      "url": "https://goone.pro/streaming.php?id=MTI4OTE3&title=Onegai+My+Melody%3A+Kuru+Kuru+Shuffle%21+Episode+18"
    },
    {
      "name": "Gogo server",
      "url": "https://goone.pro/embedplus?id=MTI4OTE3&token=CUvk_LOtX5m9RHEzkbiCqw&expires=1697897203"
    },
    {
      "name": "Streamwish",
      "url": "https://awish.pro/e/tv1munney1e8"
    },
    {
      "name": "Server Hydrax",
      "url": "https://hydrax.net/watch?v=ar4zFovE49"
    },
    {
      "name": "Mp4Upload",
      "url": "https://www.mp4upload.com/embed-3a0y3gz3u68h.html"
    },
    {
      "name": "Doodstream",
      "url": "https://dood.wf/e/wgzg0zde92yr"
    },
    {
      "name": "Filelions",
      "url": "https://alions.pro/v/16g3if2qicg0"
    }
  ],
  [
    {
      "name": "Vidstreaming",
      "url": "https://goone.pro/streaming.php?id=MTI4OTE4&title=Onegai+My+Melody%3A+Kuru+Kuru+Shuffle%21+Episode+19"
    },
    {
      "name": "Gogo server",
      "url": "https://goone.pro/embedplus?id=MTI4OTE4&token=UqOsd4_2vGUTFoEbD3BBFw&expires=1697897203"
    },
    {
      "name": "Streamwish",
      "url": "https://awish.pro/e/uyg7pjzctghj"
    },
    {
      "name": "Server Hydrax",
      "url": "https://hydrax.net/watch?v=DPGte0j5I7g"
    },
    {
      "name": "Mp4Upload",
      "url": "https://www.mp4upload.com/embed-9bzqocxjr9nz.html"
    },
    {
      "name": "Doodstream",
      "url": "https://dood.wf/e/d21pslpxiiwg"
    },
    {
      "name": "Filelions",
      "url": "https://alions.pro/v/fpctypc5len2"
    }
  ],
  [
    {
      "name": "Vidstreaming",
      "url": "https://goone.pro/streaming.php?id=MTI4OTE5&title=Onegai+My+Melody%3A+Kuru+Kuru+Shuffle%21+Episode+20"
    },
    {
      "name": "Gogo server",
      "url": "https://goone.pro/embedplus?id=MTI4OTE5&token=eQ9F2BXbmRVprk0W2uHVdg&expires=1697897203"
    },
    {
      "name": "Streamwish",
      "url": "https://awish.pro/e/zvgt59upatgb"
    },
    {
      "name": "Server Hydrax",
      "url": "https://hydrax.net/watch?v=7iQHMUJaI"
    },
    {
      "name": "Mp4Upload",
      "url": "https://www.mp4upload.com/embed-4c5dvc7mg6cz.html"
    },
    {
      "name": "Doodstream",
      "url": "https://dood.wf/e/ehfrqg7gb23r"
    },
    {
      "name": "Filelions",
      "url": "https://alions.pro/v/evz2tixa6oa1"
    }
  ],
  [
    {
      "name": "Vidstreaming",
      "url": "https://goone.pro/streaming.php?id=MTI4OTIw&title=Onegai+My+Melody%3A+Kuru+Kuru+Shuffle%21+Episode+21"
    },
    {
      "name": "Gogo server",
      "url": "https://goone.pro/embedplus?id=MTI4OTIw&token=RHXUCLZ34FAz-OZ0dRHA6A&expires=1697897203"
    },
    {
      "name": "Streamwish",
      "url": "https://awish.pro/e/m8fum0zwvx8x"
    },
    {
      "name": "Server Hydrax",
      "url": "https://hydrax.net/watch?v=1pflt2zKt"
    },
    {
      "name": "Mp4Upload",
      "url": "https://www.mp4upload.com/embed-z14zgju0gczq.html"
    },
    {
      "name": "Doodstream",
      "url": "https://dood.wf/e/8ghtxsqgd2vl"
    },
    {
      "name": "Filelions",
      "url": "https://alions.pro/v/zyg1lw0dvn9z"
    }
  ],
  [
    {
      "name": "Vidstreaming",
      "url": "https://goone.pro/streaming.php?id=MTI4OTIx&title=Onegai+My+Melody%3A+Kuru+Kuru+Shuffle%21+Episode+22"
    },
    {
      "name": "Gogo server",
      "url": "https://goone.pro/embedplus?id=MTI4OTIx&token=2hjVb2KrJWTJzos0J5ydTA&expires=1697897203"
    },
    {
      "name": "Streamwish",
      "url": "https://awish.pro/e/q3tbexzlv4z5"
    },
    {
      "name": "Server Hydrax",
      "url": "https://hydrax.net/watch?v=eucoKYlng"
    },
    {
      "name": "Mp4Upload",
      "url": "https://www.mp4upload.com/embed-8cj87juuaufh.html"
    },
    {
      "name": "Doodstream",
      "url": "https://dood.wf/e/8oq3yaiqttan"
    },
    {
      "name": "Filelions",
      "url": "https://alions.pro/v/5w86ob17g8o2"
    }
  ],
  [
    {
      "name": "Vidstreaming",
      "url": "https://goone.pro/streaming.php?id=MTI4OTIy&title=Onegai+My+Melody%3A+Kuru+Kuru+Shuffle%21+Episode+23"
    },
    {
      "name": "Gogo server",
      "url": "https://goone.pro/embedplus?id=MTI4OTIy&token=-wFjWLMZzBLIAJxqWXBfsQ&expires=1697897203"
    },
    {
      "name": "Streamwish",
      "url": "https://awish.pro/e/bv1myl4292q7"
    },
    {
      "name": "Server Hydrax",
      "url": "https://hydrax.net/watch?v=YeOv48Wtl"
    },
    {
      "name": "Mp4Upload",
      "url": "https://www.mp4upload.com/embed-ae46jsrzht2r.html"
    },
    {
      "name": "Doodstream",
      "url": "https://dood.wf/e/jo339ds46oi4"
    },
    {
      "name": "Filelions",
      "url": "https://alions.pro/v/c2qk10r5iuni"
    }
  ],
  [
    {
      "name": "Vidstreaming",
      "url": "https://goone.pro/streaming.php?id=MTI4OTIz&title=Onegai+My+Melody%3A+Kuru+Kuru+Shuffle%21+Episode+24"
    },
    {
      "name": "Gogo server",
      "url": "https://goone.pro/embedplus?id=MTI4OTIz&token=TGK7YLUrN6tv3-L8kUchjQ&expires=1697897203"
    },
    {
      "name": "Streamwish",
      "url": "https://awish.pro/e/3hf4hsl71jo7"
    },
    {
      "name": "Server Hydrax",
      "url": "https://hydrax.net/watch?v=3okU0rNGd"
    },
    {
      "name": "Mp4Upload",
      "url": "https://www.mp4upload.com/embed-23f6b41u22pd.html"
    },
    {
      "name": "Doodstream",
      "url": "https://dood.wf/e/gc7kl0gnmblf"
    },
    {
      "name": "Filelions",
      "url": "https://alions.pro/v/rbjq3hdczw8v"
    }
  ],
  [
    {
      "name": "Vidstreaming",
      "url": "https://goone.pro/streaming.php?id=MTI4OTI0&title=Onegai+My+Melody%3A+Kuru+Kuru+Shuffle%21+Episode+25"
    },
    {
      "name": "Gogo server",
      "url": "https://goone.pro/embedplus?id=MTI4OTI0&token=NZKtDcXfn3GUb2JvXg0UqA&expires=1697897203"
    },
    {
      "name": "Streamwish",
      "url": "https://awish.pro/e/12dk18h89m2h"
    },
    {
      "name": "Server Hydrax",
      "url": "https://hydrax.net/watch?v=M6ecXqnWy"
    },
    {
      "name": "Mp4Upload",
      "url": "https://www.mp4upload.com/embed-0dxa7veooxsi.html"
    },
    {
      "name": "Doodstream",
      "url": "https://dood.wf/e/nfob1xpatppg"
    },
    {
      "name": "Filelions",
      "url": "https://alions.pro/v/iagiha7mp8n3"
    }
  ],
  [
    {
      "name": "Vidstreaming",
      "url": "https://goone.pro/streaming.php?id=MTI4OTI1&title=Onegai+My+Melody%3A+Kuru+Kuru+Shuffle%21+Episode+26"
    },
    {
      "name": "Gogo server",
      "url": "https://goone.pro/embedplus?id=MTI4OTI1&token=d_QsP5cCjdVrLgVVGSdFRQ&expires=1697897203"
    },
    {
      "name": "Streamwish",
      "url": "https://awish.pro/e/cglxwn5g1v5g"
    },
    {
      "name": "Server Hydrax",
      "url": "https://hydrax.net/watch?v=GIMC6ySuy"
    },
    {
      "name": "Mp4Upload",
      "url": "https://www.mp4upload.com/embed-mpp7ytr4jpge.html"
    },
    {
      "name": "Doodstream",
      "url": "https://dood.wf/e/9nvtgc3gv5x4"
    },
    {
      "name": "Filelions",
      "url": "https://alions.pro/v/r8rcyk9rdxjy"
    }
  ],
  [
    {
      "name": "Vidstreaming",
      "url": "https://goone.pro/streaming.php?id=MTI4OTI2&title=Onegai+My+Melody%3A+Kuru+Kuru+Shuffle%21+Episode+27"
    },
    {
      "name": "Gogo server",
      "url": "https://goone.pro/embedplus?id=MTI4OTI2&token=sbLCO1xdTa_hMs2jwSk1Qg&expires=1697897203"
    },
    {
      "name": "Streamwish",
      "url": "https://awish.pro/e/svg1v7xrxe2a"
    },
    {
      "name": "Server Hydrax",
      "url": "https://hydrax.net/watch?v=uTHfX_KE4O"
    },
    {
      "name": "Mp4Upload",
      "url": "https://www.mp4upload.com/embed-uihmhe9bnjaa.html"
    },
    {
      "name": "Doodstream",
      "url": "https://dood.wf/e/b5x5i89rkart"
    },
    {
      "name": "Filelions",
      "url": "https://alions.pro/v/w4z7gi3fbinl"
    }
  ],
  [
    {
      "name": "Vidstreaming",
      "url": "https://goone.pro/streaming.php?id=MTI4OTI3&title=Onegai+My+Melody%3A+Kuru+Kuru+Shuffle%21+Episode+28"
    },
    {
      "name": "Gogo server",
      "url": "https://goone.pro/embedplus?id=MTI4OTI3&token=C9IdZS3pMzNmMpkqLKWBcg&expires=1697897203"
    },
    {
      "name": "Streamwish",
      "url": "https://awish.pro/e/7ttrqj69av8h"
    },
    {
      "name": "Server Hydrax",
      "url": "https://hydrax.net/watch?v=NPlcsCNaq"
    },
    {
      "name": "Mp4Upload",
      "url": "https://www.mp4upload.com/embed-h7knpk6ffh6c.html"
    },
    {
      "name": "Doodstream",
      "url": "https://dood.wf/e/qonvilm0krwc"
    },
    {
      "name": "Filelions",
      "url": "https://alions.pro/v/xb5bpihl131b"
    }
  ],
  [
    {
      "name": "Vidstreaming",
      "url": "https://goone.pro/streaming.php?id=MTI4OTI4&title=Onegai+My+Melody%3A+Kuru+Kuru+Shuffle%21+Episode+29"
    },
    {
      "name": "Gogo server",
      "url": "https://goone.pro/embedplus?id=MTI4OTI4&token=pnX07W1c_e6JDPKv2PE1MQ&expires=1697897203"
    },
    {
      "name": "Streamwish",
      "url": "https://awish.pro/e/15qe109wtbz2"
    },
    {
      "name": "Server Hydrax",
      "url": "https://hydrax.net/watch?v=QJ0cQ-L_n"
    },
    {
      "name": "Mp4Upload",
      "url": "https://www.mp4upload.com/embed-dpq3boish3fg.html"
    },
    {
      "name": "Doodstream",
      "url": "https://dood.wf/e/dr1wx52uszgo"
    },
    {
      "name": "Filelions",
      "url": "https://alions.pro/v/5a0l0n3qjsdp"
    }
  ],
  [
    {
      "name": "Vidstreaming",
      "url": "https://goone.pro/streaming.php?id=MTI4OTI5&title=Onegai+My+Melody%3A+Kuru+Kuru+Shuffle%21+Episode+30"
    },
    {
      "name": "Gogo server",
      "url": "https://goone.pro/embedplus?id=MTI4OTI5&token=3hTxjCQZO9gwhDsUsZYA3A&expires=1697897203"
    },
    {
      "name": "Streamwish",
      "url": "https://awish.pro/e/t8q0xbt70gel"
    },
    {
      "name": "Server Hydrax",
      "url": "https://hydrax.net/watch?v=9xqGXVzC4S"
    },
    {
      "name": "Mp4Upload",
      "url": "https://www.mp4upload.com/embed-l49rbfre7lev.html"
    },
    {
      "name": "Doodstream",
      "url": "https://dood.wf/e/qkhr1j4lh431"
    },
    {
      "name": "Filelions",
      "url": "https://alions.pro/v/9w8fluqciw38"
    }
  ],
  [
    {
      "name": "Vidstreaming",
      "url": "https://goone.pro/streaming.php?id=MTI4OTMw&title=Onegai+My+Melody%3A+Kuru+Kuru+Shuffle%21+Episode+31"
    },
    {
      "name": "Gogo server",
      "url": "https://goone.pro/embedplus?id=MTI4OTMw&token=_rLX6-m-toxmKB0j7BbT6g&expires=1697897203"
    },
    {
      "name": "Streamwish",
      "url": "https://awish.pro/e/uh9vmbra7jmn"
    },
    {
      "name": "Server Hydrax",
      "url": "https://hydrax.net/watch?v=WkmBBSrje"
    },
    {
      "name": "Mp4Upload",
      "url": "https://www.mp4upload.com/embed-jo0u4ij1ptba.html"
    },
    {
      "name": "Doodstream",
      "url": "https://dood.wf/e/dossf075qw88"
    },
    {
      "name": "Filelions",
      "url": "https://alions.pro/v/v8tm5dt4xuuu"
    }
  ],
  [
    {
      "name": "Vidstreaming",
      "url": "https://goone.pro/streaming.php?id=MTI4OTMx&title=Onegai+My+Melody%3A+Kuru+Kuru+Shuffle%21+Episode+32"
    },
    {
      "name": "Gogo server",
      "url": "https://goone.pro/embedplus?id=MTI4OTMx&token=Yamsp9cfAl_FdC-Ibc16Hg&expires=1697897203"
    },
    {
      "name": "Streamwish",
      "url": "https://awish.pro/e/d17c998vdw72"
    },
    {
      "name": "Server Hydrax",
      "url": "https://hydrax.net/watch?v=hGQfm8uJag"
    },
    {
      "name": "Mp4Upload",
      "url": "https://www.mp4upload.com/embed-5l4ccfa3kqgb.html"
    },
    {
      "name": "Doodstream",
      "url": "https://dood.wf/e/2hmk1872ngy2"
    },
    {
      "name": "Filelions",
      "url": "https://alions.pro/v/561i8j6oskcl"
    }
  ],
  [
    {
      "name": "Vidstreaming",
      "url": "https://goone.pro/streaming.php?id=MTI4OTMy&title=Onegai+My+Melody%3A+Kuru+Kuru+Shuffle%21+Episode+33"
    },
    {
      "name": "Gogo server",
      "url": "https://goone.pro/embedplus?id=MTI4OTMy&token=OZMnKxk9XI6Q72dzELfyAQ&expires=1697897203"
    },
    {
      "name": "Streamwish",
      "url": "https://awish.pro/e/aawkfu0767v8"
    },
    {
      "name": "Server Hydrax",
      "url": "https://hydrax.net/watch?v=o2yiSpqEel"
    },
    {
      "name": "Mp4Upload",
      "url": "https://www.mp4upload.com/embed-mavl5x2sg0ab.html"
    },
    {
      "name": "Doodstream",
      "url": "https://dood.wf/e/o9gfcfqqt9ez"
    },
    {
      "name": "Filelions",
      "url": "https://alions.pro/v/p1d899nnx76y"
    }
  ],
  [
    {
      "name": "Vidstreaming",
      "url": "https://goone.pro/streaming.php?id=MTI4OTMz&title=Onegai+My+Melody%3A+Kuru+Kuru+Shuffle%21+Episode+34"
    },
    {
      "name": "Gogo server",
      "url": "https://goone.pro/embedplus?id=MTI4OTMz&token=Yq6xygAHe0flxAGkMi_mKg&expires=1697897203"
    },
    {
      "name": "Streamwish",
      "url": "https://awish.pro/e/vi3jhi4beoe3"
    },
    {
      "name": "Server Hydrax",
      "url": "https://hydrax.net/watch?v=xaNf-d8yN"
    },
    {
      "name": "Mp4Upload",
      "url": "https://www.mp4upload.com/embed-572s0eskyt6z.html"
    },
    {
      "name": "Doodstream",
      "url": "https://dood.wf/e/z8er56hj3hqk"
    },
    {
      "name": "Filelions",
      "url": "https://alions.pro/v/uggcdto6ms8b"
    }
  ],
  [
    {
      "name": "Vidstreaming",
      "url": "https://goone.pro/streaming.php?id=MTI4OTM0&title=Onegai+My+Melody%3A+Kuru+Kuru+Shuffle%21+Episode+35"
    },
    {
      "name": "Gogo server",
      "url": "https://goone.pro/embedplus?id=MTI4OTM0&token=K6gvF_AjO745L8-MKUZ4mw&expires=1697897203"
    },
    {
      "name": "Streamwish",
      "url": "https://awish.pro/e/dj6zolewg9kv"
    },
    {
      "name": "Server Hydrax",
      "url": "https://hydrax.net/watch?v=4igtYn0QrA"
    },
    {
      "name": "Mp4Upload",
      "url": "https://www.mp4upload.com/embed-pwk6uxjv8seb.html"
    },
    {
      "name": "Doodstream",
      "url": "https://dood.wf/e/qkz1c9lmf5s6"
    },
    {
      "name": "Filelions",
      "url": "https://alions.pro/v/xofb8jbfhajn"
    }
  ],
  [
    {
      "name": "Vidstreaming",
      "url": "https://goone.pro/streaming.php?id=MTI4OTM1&title=Onegai+My+Melody%3A+Kuru+Kuru+Shuffle%21+Episode+36"
    },
    {
      "name": "Gogo server",
      "url": "https://goone.pro/embedplus?id=MTI4OTM1&token=pdC6ZnfX6rtsW5O6RzSC3w&expires=1697897203"
    },
    {
      "name": "Streamwish",
      "url": "https://awish.pro/e/t1j8f9ijkn3s"
    },
    {
      "name": "Server Hydrax",
      "url": "https://hydrax.net/watch?v=nvdcsOnFW"
    },
    {
      "name": "Mp4Upload",
      "url": "https://www.mp4upload.com/embed-rcxdu97692gn.html"
    },
    {
      "name": "Doodstream",
      "url": "https://dood.wf/e/qz59cbvlwmbq"
    },
    {
      "name": "Filelions",
      "url": "https://alions.pro/v/0hdg1i16eoig"
    }
  ],
  [
    {
      "name": "Vidstreaming",
      "url": "https://goone.pro/streaming.php?id=MTI4OTM2&title=Onegai+My+Melody%3A+Kuru+Kuru+Shuffle%21+Episode+37"
    },
    {
      "name": "Gogo server",
      "url": "https://goone.pro/embedplus?id=MTI4OTM2&token=zecxjQ3RuJM20UGx105WIA&expires=1697897203"
    },
    {
      "name": "Streamwish",
      "url": "https://awish.pro/e/ovu4rq7a4dcm"
    },
    {
      "name": "Server Hydrax",
      "url": "https://hydrax.net/watch?v=1s5w8AdUM"
    },
    {
      "name": "Mp4Upload",
      "url": "https://www.mp4upload.com/embed-5v4zmdq4j6ip.html"
    },
    {
      "name": "Doodstream",
      "url": "https://dood.wf/e/9lvlbgppb2ia"
    },
    {
      "name": "Filelions",
      "url": "https://alions.pro/v/r9s4gyqc51ap"
    }
  ],
  [
    {
      "name": "Vidstreaming",
      "url": "https://goone.pro/streaming.php?id=MTI4OTM3&title=Onegai+My+Melody%3A+Kuru+Kuru+Shuffle%21+Episode+38"
    },
    {
      "name": "Gogo server",
      "url": "https://goone.pro/embedplus?id=MTI4OTM3&token=Bjw6ovkvSmo3QZCDa_yoyA&expires=1697897203"
    },
    {
      "name": "Streamwish",
      "url": "https://awish.pro/e/rcxfmlnx7vue"
    },
    {
      "name": "Server Hydrax",
      "url": "https://hydrax.net/watch?v=qDdNtMbvHV"
    },
    {
      "name": "Mp4Upload",
      "url": "https://www.mp4upload.com/embed-8mzif4p9ywdt.html"
    },
    {
      "name": "Doodstream",
      "url": "https://dood.wf/e/qmb3fj98j0qf"
    },
    {
      "name": "Filelions",
      "url": "https://alions.pro/v/8rtj1i3au9ix"
    }
  ],
  [
    {
      "name": "Vidstreaming",
      "url": "https://goone.pro/streaming.php?id=MTI4OTM4&title=Onegai+My+Melody%3A+Kuru+Kuru+Shuffle%21+Episode+39"
    },
    {
      "name": "Gogo server",
      "url": "https://goone.pro/embedplus?id=MTI4OTM4&token=_5gPxYE9Y9_AJCK9ds80-w&expires=1697897203"
    },
    {
      "name": "Streamwish",
      "url": "https://awish.pro/e/veo4nkfmi74w"
    },
    {
      "name": "Server Hydrax",
      "url": "https://hydrax.net/watch?v=N32S1CL42"
    },
    {
      "name": "Mp4Upload",
      "url": "https://www.mp4upload.com/embed-e80ncmb87ujr.html"
    },
    {
      "name": "Doodstream",
      "url": "https://dood.wf/e/twnv5e1s8jfv"
    },
    {
      "name": "Filelions",
      "url": "https://alions.pro/v/2y1m8yra45yv"
    }
  ],
  [
    {
      "name": "Vidstreaming",
      "url": "https://goone.pro/streaming.php?id=MTI4OTM5&title=Onegai+My+Melody%3A+Kuru+Kuru+Shuffle%21+Episode+40"
    },
    {
      "name": "Gogo server",
      "url": "https://goone.pro/embedplus?id=MTI4OTM5&token=TEa8d6T9e35CnmpxpGFtYA&expires=1697897203"
    },
    {
      "name": "Streamwish",
      "url": "https://awish.pro/e/p3taolytkmkw"
    },
    {
      "name": "Server Hydrax",
      "url": "https://hydrax.net/watch?v=syLgzzjJz8"
    },
    {
      "name": "Mp4Upload",
      "url": "https://www.mp4upload.com/embed-00w094vsr7l1.html"
    },
    {
      "name": "Doodstream",
      "url": "https://dood.wf/e/auug1v3v357u"
    },
    {
      "name": "Filelions",
      "url": "https://alions.pro/v/p1pgp56ajt85"
    }
  ],
  [
    {
      "name": "Vidstreaming",
      "url": "https://goone.pro/streaming.php?id=MTI4OTQw&title=Onegai+My+Melody%3A+Kuru+Kuru+Shuffle%21+Episode+41"
    },
    {
      "name": "Gogo server",
      "url": "https://goone.pro/embedplus?id=MTI4OTQw&token=0YW1LQEhEU56n2pFlLtbag&expires=1697897203"
    },
    {
      "name": "Streamwish",
      "url": "https://awish.pro/e/m510k8x4yd91"
    },
    {
      "name": "Server Hydrax",
      "url": "https://hydrax.net/watch?v=16JbSfhgS"
    },
    {
      "name": "Mp4Upload",
      "url": "https://www.mp4upload.com/embed-lo0ycxvfeqak.html"
    },
    {
      "name": "Doodstream",
      "url": "https://dood.wf/e/khbfx4pf0vzs"
    },
    {
      "name": "Filelions",
      "url": "https://alions.pro/v/470eqw7djk63"
    }
  ],
  [
    {
      "name": "Vidstreaming",
      "url": "https://goone.pro/streaming.php?id=MTI4OTQx&title=Onegai+My+Melody%3A+Kuru+Kuru+Shuffle%21+Episode+42"
    },
    {
      "name": "Gogo server",
      "url": "https://goone.pro/embedplus?id=MTI4OTQx&token=Y2aMWbU2bpWcuRFDEHpQNQ&expires=1697897203"
    },
    {
      "name": "Streamwish",
      "url": "https://awish.pro/e/ndrtxeixzt3h"
    },
    {
      "name": "Server Hydrax",
      "url": "https://hydrax.net/watch?v=rS4vsESi7"
    },
    {
      "name": "Mp4Upload",
      "url": "https://www.mp4upload.com/embed-04n6ku745qgu.html"
    },
    {
      "name": "Doodstream",
      "url": "https://dood.wf/e/34k7fxic6uca"
    },
    {
      "name": "Filelions",
      "url": "https://alions.pro/v/50uu8u6m77nd"
    }
  ],
  [
    {
      "name": "Vidstreaming",
      "url": "https://goone.pro/streaming.php?id=MTI4OTQy&title=Onegai+My+Melody%3A+Kuru+Kuru+Shuffle%21+Episode+43"
    },
    {
      "name": "Gogo server",
      "url": "https://goone.pro/embedplus?id=MTI4OTQy&token=KT9EE1YCg3__ItQw8Gp8Tw&expires=1697897203"
    },
    {
      "name": "Streamwish",
      "url": "https://awish.pro/e/n8264nz470df"
    },
    {
      "name": "Server Hydrax",
      "url": "https://hydrax.net/watch?v=zCeIK74k_"
    },
    {
      "name": "Mp4Upload",
      "url": "https://www.mp4upload.com/embed-cqx2c04fzhe0.html"
    },
    {
      "name": "Doodstream",
      "url": "https://dood.wf/e/d0bdld0v3r6n"
    },
    {
      "name": "Filelions",
      "url": "https://alions.pro/v/08rpgcrrshgq"
    }
  ],
  [
    {
      "name": "Vidstreaming",
      "url": "https://goone.pro/streaming.php?id=MTI4OTQz&title=Onegai+My+Melody%3A+Kuru+Kuru+Shuffle%21+Episode+44"
    },
    {
      "name": "Gogo server",
      "url": "https://goone.pro/embedplus?id=MTI4OTQz&token=AVPzBL9UCiIUOdTnwfFw8w&expires=1697897203"
    },
    {
      "name": "Streamwish",
      "url": "https://awish.pro/e/ly03h4j7g3db"
    },
    {
      "name": "Server Hydrax",
      "url": "https://hydrax.net/watch?v=FTHWa3EBI"
    },
    {
      "name": "Mp4Upload",
      "url": "https://www.mp4upload.com/embed-urfmu3nzun1g.html"
    },
    {
      "name": "Doodstream",
      "url": "https://dood.wf/e/amolfoihu1wa"
    },
    {
      "name": "Filelions",
      "url": "https://alions.pro/v/eaxi489mn9a5"
    }
  ],
  [
    {
      "name": "Vidstreaming",
      "url": "https://goone.pro/streaming.php?id=MTI4OTQ0&title=Onegai+My+Melody%3A+Kuru+Kuru+Shuffle%21+Episode+45"
    },
    {
      "name": "Gogo server",
      "url": "https://goone.pro/embedplus?id=MTI4OTQ0&token=CFjRonubEzKdJIPNQ_KAHQ&expires=1697897203"
    },
    {
      "name": "Streamwish",
      "url": "https://awish.pro/e/juz5ti8vb33c"
    },
    {
      "name": "Server Hydrax",
      "url": "https://hydrax.net/watch?v=TIa8GMB-C"
    },
    {
      "name": "Mp4Upload",
      "url": "https://www.mp4upload.com/embed-no4llaqjhaei.html"
    },
    {
      "name": "Doodstream",
      "url": "https://dood.wf/e/uj47gqybwjtx"
    },
    {
      "name": "Filelions",
      "url": "https://alions.pro/v/ta6h295kh039"
    }
  ],
  [
    {
      "name": "Vidstreaming",
      "url": "https://goone.pro/streaming.php?id=MTI4OTQ1&title=Onegai+My+Melody%3A+Kuru+Kuru+Shuffle%21+Episode+46"
    },
    {
      "name": "Gogo server",
      "url": "https://goone.pro/embedplus?id=MTI4OTQ1&token=4-O2OP3c1rMDOrDZV6wAtw&expires=1697897203"
    },
    {
      "name": "Streamwish",
      "url": "https://awish.pro/e/x8zzm24d6grf"
    },
    {
      "name": "Server Hydrax",
      "url": "https://hydrax.net/watch?v=35EpXYGzZp"
    },
    {
      "name": "Mp4Upload",
      "url": "https://www.mp4upload.com/embed-ohs0nnzik4iy.html"
    },
    {
      "name": "Doodstream",
      "url": "https://dood.wf/e/4adzzj98mds4"
    },
    {
      "name": "Filelions",
      "url": "https://alions.pro/v/ede0bfz5uh2p"
    }
  ],
  [
    {
      "name": "Vidstreaming",
      "url": "https://goone.pro/streaming.php?id=MTI4OTQ2&title=Onegai+My+Melody%3A+Kuru+Kuru+Shuffle%21+Episode+47"
    },
    {
      "name": "Gogo server",
      "url": "https://goone.pro/embedplus?id=MTI4OTQ2&token=ENOMR8qkVLt6gCDMGS_XWw&expires=1697897203"
    },
    {
      "name": "Streamwish",
      "url": "https://awish.pro/e/q4dlfe6n0bdq"
    },
    {
      "name": "Server Hydrax",
      "url": "https://hydrax.net/watch?v=AIf3QguDU3"
    },
    {
      "name": "Mp4Upload",
      "url": "https://www.mp4upload.com/embed-b8pq02cnwdy3.html"
    },
    {
      "name": "Doodstream",
      "url": "https://dood.wf/e/1ybepwg8b0zi"
    },
    {
      "name": "Filelions",
      "url": "https://alions.pro/v/cbl1ho4q1fnf"
    }
  ],
  [
    {
      "name": "Vidstreaming",
      "url": "https://goone.pro/streaming.php?id=MTI4OTQ3&title=Onegai+My+Melody%3A+Kuru+Kuru+Shuffle%21+Episode+48"
    },
    {
      "name": "Gogo server",
      "url": "https://goone.pro/embedplus?id=MTI4OTQ3&token=Wq7_ceJWPmdXauXRJseXtQ&expires=1697897203"
    },
    {
      "name": "Streamwish",
      "url": "https://awish.pro/e/0cqlvotdo5hi"
    },
    {
      "name": "Server Hydrax",
      "url": "https://hydrax.net/watch?v=daWdh7A-G"
    },
    {
      "name": "Mp4Upload",
      "url": "https://www.mp4upload.com/embed-wzpjuzadaauo.html"
    },
    {
      "name": "Doodstream",
      "url": "https://dood.wf/e/p4gy7p6kxmkj"
    },
    {
      "name": "Filelions",
      "url": "https://alions.pro/v/cl8398kbzkz8"
    }
  ],
  [
    {
      "name": "Vidstreaming",
      "url": "https://goone.pro/streaming.php?id=MTI4OTQ4&title=Onegai+My+Melody%3A+Kuru+Kuru+Shuffle%21+Episode+49"
    },
    {
      "name": "Gogo server",
      "url": "https://goone.pro/embedplus?id=MTI4OTQ4&token=I68C2l0nh4lIhTXJuGO2Qw&expires=1697897203"
    },
    {
      "name": "Streamwish",
      "url": "https://awish.pro/e/ml6hsa5twlpj"
    },
    {
      "name": "Server Hydrax",
      "url": "https://hydrax.net/watch?v=IC321lApL"
    },
    {
      "name": "Mp4Upload",
      "url": "https://www.mp4upload.com/embed-ygn8eibvemx9.html"
    },
    {
      "name": "Doodstream",
      "url": "https://dood.wf/e/chdvaogtypdz"
    },
    {
      "name": "Filelions",
      "url": "https://alions.pro/v/bzgtf650jotc"
    }
  ],
  [
    {
      "name": "Vidstreaming",
      "url": "https://goone.pro/streaming.php?id=MTI4OTQ5&title=Onegai+My+Melody%3A+Kuru+Kuru+Shuffle%21+Episode+50"
    },
    {
      "name": "Gogo server",
      "url": "https://goone.pro/embedplus?id=MTI4OTQ5&token=5s50IYHmqEgpn-wNc57Oug&expires=1697897203"
    },
    {
      "name": "Streamwish",
      "url": "https://awish.pro/e/z4ews9lryuox"
    },
    {
      "name": "Server Hydrax",
      "url": "https://hydrax.net/watch?v=BF3TQPIe3"
    },
    {
      "name": "Mp4Upload",
      "url": "https://www.mp4upload.com/embed-ue0q77r72o6q.html"
    },
    {
      "name": "Doodstream",
      "url": "https://dood.wf/e/a6vl3pi318pm"
    },
    {
      "name": "Filelions",
      "url": "https://alions.pro/v/h0cb46r601i1"
    }
  ],
  [
    {
      "name": "Vidstreaming",
      "url": "https://goone.pro/streaming.php?id=MTI4OTUw&title=Onegai+My+Melody%3A+Kuru+Kuru+Shuffle%21+Episode+51"
    },
    {
      "name": "Gogo server",
      "url": "https://goone.pro/embedplus?id=MTI4OTUw&token=ItQ3aQAlJPqmfPVmr3j4SQ&expires=1697897203"
    },
    {
      "name": "Streamwish",
      "url": "https://awish.pro/e/t1tn64chure1"
    },
    {
      "name": "Server Hydrax",
      "url": "https://hydrax.net/watch?v=CXqX27zibe"
    },
    {
      "name": "Mp4Upload",
      "url": "https://www.mp4upload.com/embed-eozn2zm7551e.html"
    },
    {
      "name": "Doodstream",
      "url": "https://dood.wf/e/skmh3wkea7eu"
    },
    {
      "name": "Filelions",
      "url": "https://alions.pro/v/5rks1ybhnc7c"
    }
  ],
  [
    {
      "name": "Vidstreaming",
      "url": "https://goone.pro/streaming.php?id=MTI4OTUx&title=Onegai+My+Melody%3A+Kuru+Kuru+Shuffle%21+Episode+52"
    },
    {
      "name": "Gogo server",
      "url": "https://goone.pro/embedplus?id=MTI4OTUx&token=m0NDibJk2QwPCxcqi0SR0g&expires=1697897203"
    },
    {
      "name": "Streamwish",
      "url": "https://awish.pro/e/cyimn1fucnts"
    },
    {
      "name": "Server Hydrax",
      "url": "https://hydrax.net/watch?v=QzRR4G6AOo"
    },
    {
      "name": "Mp4Upload",
      "url": "https://www.mp4upload.com/embed-g3241p3dr9m5.html"
    },
    {
      "name": "Doodstream",
      "url": "https://dood.wf/e/8ul8v3biihh3"
    },
    {
      "name": "Filelions",
      "url": "https://alions.pro/v/7dqdwgdul33z"
    }
  ]
]